recursive_monkey_patch.py
recursive_monkey_patch-0.4.0.dist-info/DESCRIPTION.rst
recursive_monkey_patch-0.4.0.dist-info/METADATA
recursive_monkey_patch-0.4.0.dist-info/RECORD
recursive_monkey_patch-0.4.0.dist-info/WHEEL
recursive_monkey_patch-0.4.0.dist-info/metadata.json
recursive_monkey_patch-0.4.0.dist-info/top_level.txt
