Metadata-Version: 2.0
Name: recursive-monkey-patch
Version: 0.4.0
Summary: Recursive Monkey Patching
Home-page: https://github.com/nthiery/recursive-monkey-patch
Author: Nicolas M. Thiéry
Author-email: nthiery@users.sf.net
License: GPLv2+
Keywords: packaging development
Platform: UNKNOWN
Classifier: Development Status :: 3 - Alpha
Classifier: Intended Audience :: Developers
Classifier: Intended Audience :: Science/Research
Classifier: Topic :: Software Development :: Build Tools
Classifier: License :: OSI Approved :: GNU General Public License v2 or later (GPLv2+)
Classifier: Programming Language :: Python :: 2
Classifier: Programming Language :: Python :: 3
